officechunker/__init__.py
officechunker/chunkers.py
officechunker/cli.py
officechunker/converter.py
officechunker/file_handlers.py
officechunker/process.py
officechunker-0.2.0.dist-info/METADATA
officechunker-0.2.0.dist-info/WHEEL
officechunker-0.2.0.dist-info/entry_points.txt
officechunker-0.2.0.dist-info/top_level.txt
officechunker-0.2.0.dist-info/RECORD
